foai_model/__init__.py
foai_model/config/__init__.py
foai_model/config/config.py
foai_model/file_reader/__init__.py
foai_model/file_reader/reader.py
foai_model/logger/__init__.py
foai_model/logger/setup.py
foai_model/predict/__init__.py
foai_model/predict/predict.py
foai_model/preprocessing/__init__.py
foai_model/preprocessing/categories.py
foai_model/preprocessing/preprocess.py
foai_model/train/__init__.py
foai_model/train/train.py
foai_model/utils/__init__.py
foai_model/utils/device_info.py
foai_model-1.6.1.dist-info/LICENSE
foai_model-1.6.1.dist-info/METADATA
foai_model-1.6.1.dist-info/WHEEL
foai_model-1.6.1.dist-info/entry_points.txt
foai_model-1.6.1.dist-info/RECORD
