Metadata-Version: 2.3
Name: foai_model
Version: 1.6.1
Summary: 
Author: Dariusz Homa
Author-email: dariuszhoma7@gmail.com
Requires-Python: >=3.12,<4.0
Classifier: Programming Language :: Python :: 3
Classifier: Programming Language :: Python :: 3.12
Classifier: Programming Language :: Python :: 3.13
Requires-Dist: accelerate (>=1.6.0,<2.0.0)
Requires-Dist: argparse (>=1.4.0,<2.0.0)
Requires-Dist: bs4 (>=0.0.2,<0.0.3)
Requires-Dist: datasets (>=3.5.0,<4.0.0)
Requires-Dist: dotenv (>=0.9.9,<0.10.0)
Requires-Dist: hf-xet (>=1.0.0,<2.0.0)
Requires-Dist: huggingface-hub (>=0.30.1,<0.31.0)
Requires-Dist: matplotlib (>=3.10.1,<4.0.0)
Requires-Dist: nltk (>=3.9.1,<4.0.0)
Requires-Dist: numpy (>=2.2.4,<3.0.0)
Requires-Dist: pandas (>=2.2.3,<3.0.0)
Requires-Dist: scikit-learn (>=1.6.1,<2.0.0)
Requires-Dist: torch (==2.5.1)
Requires-Dist: torchvision (==0.20.1)
Requires-Dist: transformers (>=4.51.0,<5.0.0)
Requires-Dist: wordcloud (>=1.9.4,<2.0.0)
